fad_pytorch/__init__.py
fad_pytorch/_modidx.py
fad_pytorch/fad_embed.py
fad_pytorch/fad_gen.py
fad_pytorch/fad_score.py
fad_pytorch/pann.py
fad_pytorch/pann_pytorch_utils.py
fad_pytorch/sqrtm.py
fad_pytorch-0.0.6.dist-info/LICENSE
fad_pytorch-0.0.6.dist-info/METADATA
fad_pytorch-0.0.6.dist-info/WHEEL
fad_pytorch-0.0.6.dist-info/entry_points.txt
fad_pytorch-0.0.6.dist-info/top_level.txt
fad_pytorch-0.0.6.dist-info/RECORD
