Metadata-Version: 2.1
Name: fad-pytorch
Version: 0.0.6
Summary: Frechet Audio Distance evaluation in PyTorch
Home-page: https://github.com/drscotthawley/fad_pytorch
Author: Scott H. Hawley
Author-email: scott.hawley@belmont.edu
License: Apache Software License 2.0
Keywords: nbdev jupyter notebook python
Classifier: Development Status :: 4 - Beta
Classifier: Intended Audience :: Developers
Classifier: Natural Language :: English
Classifier: Programming Language :: Python :: 3.7
Classifier: Programming Language :: Python :: 3.8
Classifier: Programming Language :: Python :: 3.9
Classifier: Programming Language :: Python :: 3.10
Classifier: License :: OSI Approved :: Apache Software License
Requires-Python: >=3.7
License-File: LICENSE
Requires-Dist: aeiou
Requires-Dist: torch (>=1.13.1)
Requires-Dist: torchaudio (>=0.13.1)
Requires-Dist: laion-clap
Requires-Dist: accelerate
Requires-Dist: torchlibrosa
Requires-Dist: torchopenl3
Provides-Extra: dev
